admath1/__init__.py
admath1/area.py
admath1/parameter.py
admath1/trignometry.py
admath1-0.0.3.dist-info/LICENSE.txt
admath1-0.0.3.dist-info/METADATA
admath1-0.0.3.dist-info/WHEEL
admath1-0.0.3.dist-info/top_level.txt
admath1-0.0.3.dist-info/RECORD
