Metadata-Version: 2.1
Name: admath1
Version: 0.0.3
Summary: maths library with some intermediate and advanced function
Home-page: 
Author: Subhash Kumar
Author-email: subhashfreelancer2004@gmail.com
License: MIT
Keywords: maths,advance math,math,math formula,formula
Classifier: Development Status :: 5 - Production/Stable
Classifier: Intended Audience :: Education
Classifier: Operating System :: Microsoft :: Windows :: Windows 10
Classifier: Operating System :: Unix
Classifier: Operating System :: MacOS :: MacOS X
Classifier: License :: OSI Approved :: MIT License
Classifier: Programming Language :: Python :: 3
License-File: LICENSE.txt
